powerbrain/__init__.py
powerbrain/powerbrain.py
powerbrain-0.1.0.dist-info/LICENSE
powerbrain-0.1.0.dist-info/WHEEL
powerbrain-0.1.0.dist-info/METADATA
powerbrain-0.1.0.dist-info/RECORD
